MANIFEST.in
README.md
setup.py
Firstmysite_Jia/__init__.py
Firstmysite_Jia/manage.py
Firstmysite_Jia.egg-info/PKG-INFO
Firstmysite_Jia.egg-info/SOURCES.txt
Firstmysite_Jia.egg-info/dependency_links.txt
Firstmysite_Jia.egg-info/requires.txt
Firstmysite_Jia.egg-info/top_level.txt
Firstmysite_Jia/FirstApp/__init__.py
Firstmysite_Jia/FirstApp/admin.py
Firstmysite_Jia/FirstApp/apps.py
Firstmysite_Jia/FirstApp/models.py
Firstmysite_Jia/FirstApp/tests.py
Firstmysite_Jia/FirstApp/views.py
Firstmysite_Jia/FirstApp/migrations/__init__.py
Firstmysite_Jia/Firstmysite_Jia/__init__.py
Firstmysite_Jia/Firstmysite_Jia/settings.py
Firstmysite_Jia/Firstmysite_Jia/urls.py
Firstmysite_Jia/Firstmysite_Jia/wsgi.py