Metadata-Version: 1.0
Name: Firstmysite-Jia
Version: 1.0.3
Summary: ap monitor system
Home-page: UNKNOWN
Author: Darren_liu
Author-email: Darren_Liu@syscom.com.tw
License: UNKNOWN
Platform: UNKNOWN
